{
    "all_levels": [
        107.97,
        108.63,
        108.96,
        109.29,
        109.62,
        109.96,
        110.29,
        110.63,
        110.97,
        111.3,
        111.98,
        112.33,
        112.67,
        113.01,
        113.36,
        113.7,
        114.05,
        114.4,
        114.75,
        115.1,
        115.56,
        115.7,
        115.72,
        115.77,
        115.8,
        115.82,
        115.85,
        115.9,
        115.98,
        116.23,
        120.54,
        120.63,
        120.74,
        120.77,
        120.78,
        120.79,
        120.81,
        120.88,
        120.9,
        120.97,
        121.03,
        121.07,
        121.12,
        121.15,
        121.17,
        121.29,
        121.33,
        121.4,
        121.42,
        121.47,
        121.81,
        121.83,
        122.16,
        122.81,
        123.14,
        123.46,
        123.5,
        123.68,
        123.84,
        123.96,
        124.03,
        124.04,
        124.13,
        124.3,
        124.64,
        124.98,
        125.32,
        125.67,
        126.01,
        126.36,
        126.54,
        126.88,
        127.21,
        127.55,
        127.89,
        128.23,
        128.57,
        128.91,
        129.04,
        129.16,
        129.25,
        129.36,
        132.48,
        132.59,
        132.61,
        132.65,
        132.68,
        132.7,
        132.71,
        132.74,
        132.76,
        132.82,
        135.7,
        135.88,
        136.04,
        136.3,
        136.5,
        136.71,
        136.91,
        137.05,
        137.33,
        137.4,
        137.74,
        137.75,
        138.08,
        138.17,
        138.59,
        139.01,
        139.44,
        139.86,
        139.9,
        139.98,
        139.99,
        140.05,
        140.1,
        140.18,
        140.26,
        140.29,
        140.3,
        140.32,
        140.4,
        140.49,
        140.59,
        140.68,
        140.72,
        141.15,
        143.46,
        143.58,
        143.99,
        144.11,
        145.99,
        146.03,
        146.08,
        146.12,
        146.2,
        146.22,
        146.61,
        146.75,
        146.86,
        146.99,
        147.07,
        147.12,
        147.29,
        147.38,
        147.65,
        147.91,
        148.17,
        149.76,
        149.94,
        150.03,
        150.05,
        150.18,
        150.29,
        150.31,
        150.36,
        150.44,
        150.46,
        150.51,
        150.53,
        150.54,
        150.56,
        150.57,
        150.58,
        150.59,
        150.61,
        150.62,
        150.65,
        150.71,
        150.72,
        150.98,
        151.1,
        151.24,
        151.28,
        151.39,
        151.43,
        151.5,
        151.53,
        151.59,
        151.66,
        151.67,
        151.68,
        151.77,
        151.92,
        151.94,
        151.96,
        154.35,
        154.63,
        154.81,
        154.9,
        154.97,
        155.07,
        155.14,
        155.15,
        155.18,
        155.22,
        155.31,
        155.32,
        155.34,
        155.45,
        155.52,
        155.58,
        156.0,
        156.43,
        159.64
    ],
    "latest_levels": [
        132.71,
        139.9,
        159.64
    ],
    "channel": {
        "start_date": "2024-12-23 00:00:00",
        "end_date": "2025-07-09 00:00:00",
        "start_upper": 146.24,
        "start_lower": 120.87,
        "end_upper": 164.16,
        "end_lower": 138.8
    }
}