{
    "all_levels": [
        850.01,
        850.1,
        850.16,
        850.39,
        850.53,
        851.07,
        851.21,
        851.7,
        851.75,
        852.04,
        852.16,
        852.28,
        852.33,
        852.43,
        852.5,
        852.52,
        853.08,
        853.29,
        854.46,
        861.52,
        862.7,
        863.88,
        865.07,
        865.84,
        866.63,
        872.18,
        872.97,
        873.17,
        873.77,
        874.01,
        874.34,
        874.56,
        874.85,
        919.68,
        919.72,
        919.84,
        919.93,
        920.17,
        944.8,
        944.85,
        945.0,
        945.08,
        945.15,
        945.31,
        945.35,
        945.46,
        946.98,
        946.99,
        947.39,
        947.81,
        947.83,
        948.12,
        948.28,
        949.11,
        949.32,
        950.4,
        951.69,
        952.98,
        954.28,
        959.79,
        959.9,
        959.91,
        959.96,
        960.13,
        960.18,
        961.37,
        962.69,
        962.76,
        963.16,
        963.54,
        963.83,
        964.1,
        969.74,
        969.82,
        969.83,
        969.86,
        969.91,
        970.03,
        970.06,
        973.0,
        973.72,
        973.89,
        974.7,
        974.76,
        974.78,
        974.81,
        975.0,
        975.06,
        975.07,
        975.13,
        975.19,
        975.2,
        975.3,
        975.62,
        975.65,
        975.92,
        976.24,
        976.25,
        977.56,
        978.21,
        978.86,
        979.52,
        979.67,
        979.75,
        979.81,
        979.82,
        979.91,
        979.98,
        979.99,
        980.02,
        980.04,
        980.21,
        980.23,
        980.88,
        982.08,
        983.29,
        983.62,
        984.3,
        984.84,
        984.87,
        984.88,
        984.89,
        984.93,
        985.01,
        985.16,
        985.2,
        989.77,
        989.84,
        989.89,
        989.9,
        989.93,
        989.99,
        990.04,
        990.07,
        990.24,
        990.51,
        991.15,
        994.88,
        994.9,
        994.99,
        995.03,
        995.12,
        995.13,
        995.14,
        995.17,
        999.85,
        999.89,
        999.95,
        1000.15,
        1000.2,
        1000.28,
        1001.16,
        1003.37,
        1004.73,
        1005.85,
        1006.09,
        1006.89,
        1007.15,
        1007.17,
        1007.26,
        1007.46,
        1008.62,
        1008.82,
        1008.92,
        1009.99,
        1010.1,
        1010.71,
        1010.79,
        1010.91,
        1010.95,
        1011.08,
        1011.89,
        1013.24,
        1015.41,
        1016.22,
        1016.4,
        1016.7,
        1016.74,
        1017.24,
        1017.65,
        1017.78,
        1018.61,
        1018.93,
        1019.38,
        1019.43,
        1019.75,
        1020.21,
        1063.4,
        1063.84,
        1064.43,
        1064.46,
        1064.53,
        1064.55,
        1064.68,
        1064.71,
        1064.74,
        1064.83,
        1064.95,
        1064.96,
        1065.03,
        1065.04,
        1065.06,
        1065.14,
        1065.15,
        1065.19,
        1065.21,
        1065.23,
        1065.24,
        1065.25,
        1065.34,
        1065.57,
        1065.61,
        1065.64,
        1065.79,
        1065.94,
        1066.16,
        1066.38,
        1066.41,
        1066.49,
        1066.52,
        1066.57,
        1067.93,
        1068.85,
        1071.14,
        1073.43,
        1075.72,
        1078.03,
        1084.96,
        1085.45,
        1086.92,
        1087.28,
        1088.4,
        1089.61,
        1089.87,
        1090.44,
        1091.27,
        1091.35,
        1091.36,
        1091.89,
        1091.94,
        1093.03,
        1094.28,
        1096.62,
        1098.96,
        1101.31,
        1103.67,
        1106.03,
        1108.4,
        1132.04,
        1133.58,
        1135.12,
        1136.66,
        1139.74,
        1143.42,
        1151.87,
        1156.8,
        1159.28,
        1159.52,
        1160.13,
        1160.65,
        1160.94,
        1161.38,
        1161.41,
        1161.49,
        1162.37,
        1164.72,
        1166.83,
        1167.36,
        1167.66,
        1167.68,
        1168.04,
        1168.26,
        1168.44,
        1168.55,
        1169.07,
        1169.2,
        1169.35,
        1177.44,
        1178.67,
        1178.87,
        1179.04,
        1179.05,
        1179.26,
        1180.02,
        1322.49,
        1322.59,
        1323.13,
        1323.53,
        1326.36
    ],
    "latest_levels": [
        850.39
    ],
    "channel": {
        "start_date": "2024-12-23 00:00:00",
        "end_date": "2025-07-09 00:00:00",
        "start_upper": 926.95,
        "start_lower": 816.83,
        "end_upper": 864.25,
        "end_lower": 754.13
    }
}