{
    "all_levels": [
        190.63,
        190.7,
        190.83,
        191.03,
        191.1,
        191.28,
        191.55,
        211.17,
        211.77,
        212.42,
        212.93,
        213.32,
        213.44,
        213.86,
        213.95,
        214.36,
        214.46,
        214.56,
        214.81,
        214.83,
        214.97,
        215.35,
        215.42,
        215.47,
        215.48,
        215.53,
        215.6,
        215.62,
        215.68,
        215.69,
        215.7,
        215.72,
        215.79,
        215.96,
        215.97,
        215.99,
        216.22,
        216.76,
        217.38,
        217.57,
        217.73,
        217.74,
        217.79,
        218.88,
        291.34,
        291.45,
        291.76,
        291.85,
        292.09,
        292.22,
        292.45,
        293.62,
        294.73,
        295.51,
        295.52,
        295.7,
        295.74,
        295.84,
        295.86,
        296.09,
        296.11,
        296.2,
        296.29,
        296.59,
        296.96,
        297.32,
        298.06,
        302.69,
        302.71,
        302.96,
        303.07,
        303.17,
        303.18,
        303.21,
        303.26,
        303.44,
        303.57,
        303.67,
        303.77,
        303.87,
        303.94,
        303.95,
        304.01,
        304.23,
        304.43,
        304.64,
        304.76,
        304.99,
        305.65,
        306.18,
        306.64,
        307.19,
        307.53,
        307.76,
        308.32,
        309.37,
        310.42,
        318.68,
        319.19,
        319.36,
        319.8,
        320.16,
        320.45,
        320.79,
        321.41,
        321.64,
        321.74,
        323.03,
        323.31,
        324.18,
        324.31,
        325.21,
        325.5,
        325.6,
        325.62,
        326.9,
        327.72,
        328.2,
        328.23,
        328.82,
        329.04,
        329.21,
        329.55,
        329.86,
        329.95,
        330.05,
        330.68,
        330.72,
        331.12,
        331.49,
        332.19,
        332.31,
        333.14,
        333.96,
        334.46,
        334.72,
        334.79,
        335.34,
        335.38,
        335.52,
        335.63,
        336.58,
        336.73,
        339.03,
        341.33,
        343.66,
        346.0,
        348.35,
        349.32,
        351.64,
        353.97,
        358.69,
        360.44,
        364.87,
        370.71,
        377.9,
        380.32,
        385.22,
        387.69,
        390.18,
        392.24,
        394.74,
        395.17,
        396.71,
        396.9,
        396.95,
        397.47,
        398.07,
        398.63,
        398.73,
        399.16,
        399.69,
        399.86,
        400.52,
        401.63,
        402.01,
        402.32,
        402.44,
        403.41,
        403.7,
        404.1,
        404.13,
        404.75,
        405.72,
        406.72,
        607.36,
        608.09,
        610.9,
        613.17,
        613.73,
        613.74,
        613.76,
        613.9,
        613.97,
        614.01,
        614.44,
        614.71,
        614.83,
        615.49,
        615.84,
        615.99,
        616.15,
        616.19,
        616.32,
        616.37,
        616.97,
        1008.13,
        1013.92,
        1014.97,
        1016.86,
        1019.26,
        1023.14,
        1029.45,
        1034.43,
        1035.8,
        1038.65,
        1041.3,
        1042.31,
        1042.81,
        1044.8
    ],
    "latest_levels": [
        405.72,
        616.19,
        1008.13
    ],
    "channel": {
        "start_date": "2024-12-23 00:00:00",
        "end_date": "2025-07-09 00:00:00",
        "start_upper": 442.03,
        "start_lower": 274.57,
        "end_upper": 1225.31,
        "end_lower": 1057.86
    }
}