{
    "all_levels": [
        149.43,
        149.48,
        149.51,
        149.52,
        149.54,
        149.58,
        149.59,
        149.68,
        149.75,
        149.78,
        149.79,
        149.88,
        149.91,
        149.97,
        150.05,
        150.22,
        150.24,
        150.32,
        150.34,
        150.47,
        150.72,
        150.97,
        152.01,
        154.76,
        154.91,
        155.01,
        155.16,
        155.23,
        155.27,
        155.53,
        155.73,
        157.94,
        158.13,
        158.25,
        158.29,
        158.3,
        158.31,
        158.38,
        158.39,
        158.45,
        158.47,
        158.5,
        158.51,
        158.64,
        158.81,
        158.88,
        158.98,
        159.07,
        159.15,
        159.16,
        159.26,
        159.29,
        159.33,
        159.36,
        159.43,
        159.45,
        159.5,
        159.51,
        159.57,
        159.58,
        159.64,
        159.66,
        159.68,
        159.69,
        159.72,
        159.73,
        159.81,
        159.83,
        159.84,
        159.85,
        159.87,
        159.9,
        159.92,
        159.96,
        159.98,
        160.16,
        160.33,
        160.38,
        160.39,
        160.58,
        162.96,
        169.0,
        169.01,
        169.14,
        169.15,
        169.16,
        169.18,
        169.2,
        169.22,
        169.27,
        169.36,
        170.9,
        171.18,
        171.46,
        171.75,
        172.03,
        172.31,
        172.6,
        172.88,
        173.06,
        173.23,
        173.25,
        173.27,
        173.28,
        173.29,
        173.3,
        173.32,
        173.33,
        173.4,
        173.44,
        173.45,
        173.49,
        173.51,
        173.53,
        173.54,
        173.55,
        173.6,
        173.64,
        173.68,
        173.75,
        173.83,
        181.84,
        182.08,
        182.32,
        182.57,
        182.81,
        182.94,
        183.18,
        183.33,
        183.42,
        183.57,
        183.81,
        183.98,
        184.04,
        184.06,
        184.09,
        184.12,
        184.16,
        184.21,
        184.22,
        184.29,
        184.3,
        184.31,
        184.32,
        184.34,
        184.36,
        184.37,
        184.43,
        184.54,
        184.58,
        184.79,
        184.83,
        185.04,
        185.09,
        185.29,
        185.6,
        186.12,
        186.38,
        186.64,
        189.14,
        189.26,
        189.36,
        189.43,
        189.54,
        189.64,
        189.66,
        189.67,
        189.69,
        189.71,
        189.73,
        189.77,
        189.78,
        189.79,
        189.81,
        189.82,
        189.83,
        189.84,
        189.85,
        189.86,
        189.87,
        189.88,
        189.93,
        189.96,
        189.97,
        190.6,
        190.91,
        199.91,
        199.92,
        200.0,
        200.01,
        200.04,
        200.06,
        200.07,
        200.08,
        200.16,
        200.22,
        200.3,
        200.36,
        200.55,
        200.73,
        201.19,
        201.44,
        201.45,
        201.48,
        201.57,
        202.01,
        202.37,
        202.45,
        202.79,
        202.89,
        219.38,
        242.44,
        242.8,
        242.97,
        243.3
    ],
    "latest_levels": [
        202.79,
        219.38,
        243.3
    ],
    "channel": {
        "start_date": "2024-12-23 00:00:00",
        "end_date": "2025-07-09 00:00:00",
        "start_upper": 227.45,
        "start_lower": 174.99,
        "end_upper": 285.54,
        "end_lower": 233.08
    }
}