{
    "all_levels": [
        380.9,
        381.03,
        381.06,
        381.2,
        395.97,
        396.14,
        396.35,
        396.47,
        396.67,
        396.72,
        396.74,
        396.78,
        396.84,
        396.97,
        396.99,
        397.1,
        397.17,
        397.29,
        397.32,
        397.33,
        397.34,
        397.48,
        397.53,
        397.63,
        397.66,
        397.85,
        398.22,
        398.46,
        399.08,
        399.69,
        400.3,
        400.92,
        402.15,
        404.0,
        404.62,
        418.87,
        419.26,
        419.31,
        419.6,
        419.74,
        420.15,
        421.08,
        472.36,
        472.97,
        473.05,
        473.12,
        473.17,
        473.24,
        473.56,
        473.57,
        473.66,
        473.72,
        473.74,
        473.75,
        473.82,
        473.94,
        473.98,
        474.0,
        474.01,
        474.02,
        474.03,
        474.12,
        474.23,
        474.24,
        474.43,
        474.45,
        474.48,
        474.52,
        474.53,
        474.61,
        474.62,
        474.66,
        474.77,
        475.13,
        475.32,
        475.36,
        475.75,
        475.94,
        476.05,
        476.19,
        476.3,
        476.32,
        476.37,
        476.43,
        476.48,
        476.71,
        476.78,
        476.94,
        477.09,
        477.51,
        477.54,
        480.06,
        480.21,
        480.42,
        480.8,
        481.0,
        481.12,
        481.16,
        481.8,
        482.43,
        482.52,
        482.81,
        483.35,
        483.82,
        484.23,
        484.83,
        484.87,
        485.28,
        485.74,
        485.85,
        486.4,
        486.57,
        486.76,
        486.82,
        486.84,
        487.25,
        487.69,
        487.93,
        488.06,
        488.26,
        488.34,
        488.76,
        489.19,
        489.36,
        489.87,
        489.9,
        490.07,
        490.28,
        490.66,
        490.7,
        491.28,
        491.4,
        491.47,
        491.49,
        491.57,
        491.8,
        492.01,
        492.08,
        492.09,
        492.28,
        492.55,
        492.93,
        493.24,
        493.33,
        493.82,
        495.06,
        495.2,
        495.33,
        579.18,
        580.86,
        581.7,
        582.75,
        583.39,
        583.53,
        583.66,
        584.57,
        584.68,
        585.4,
        585.46,
        585.47,
        585.5,
        585.55,
        585.7,
        585.78,
        586.08,
        586.17,
        586.36,
        586.38,
        586.42,
        586.45,
        586.49,
        586.51,
        586.54,
        586.61,
        586.74,
        586.75,
        586.76,
        586.82,
        586.92,
        586.93,
        587.06,
        587.09,
        587.11,
        587.35,
        587.48,
        587.63,
        587.71,
        587.85,
        587.98,
        588.07,
        588.18,
        588.41,
        588.9,
        588.94,
        589.13,
        589.52,
        589.9,
        591.97,
        594.03,
        767.74,
        768.46,
        769.2,
        770.86,
        825.52,
        828.1,
        830.89,
        831.0,
        831.08,
        831.38,
        831.6,
        831.85,
        832.02,
        832.14,
        832.4,
        832.41,
        832.47,
        832.48,
        832.58,
        832.67,
        832.7,
        832.76,
        833.03,
        833.71,
        833.88,
        834.85,
        834.98,
        835.22,
        835.69,
        835.74,
        835.84,
        836.2,
        836.6,
        836.62,
        836.65,
        836.95,
        837.13,
        837.25,
        837.37,
        837.5,
        837.66,
        837.87,
        837.89,
        838.07,
        838.11,
        838.12,
        838.27,
        838.64,
        898.27,
        898.96,
        900.26,
        1012.88,
        1013.92,
        1014.89,
        1015.8,
        1016.63,
        1017.96,
        1018.35,
        1018.45,
        1018.54,
        1018.55,
        1018.65,
        1018.79,
        1018.9,
        1019.07,
        1019.23,
        1019.26,
        1019.75,
        1019.87,
        1020.19,
        1020.54,
        1020.59,
        1020.76,
        1021.1,
        1021.2,
        1021.44,
        1021.79,
        1021.91,
        1021.97,
        1022.38,
        1022.85,
        1022.88,
        1023.75,
        1024.75,
        1024.98,
        1025.38,
        1025.56,
        1026.35,
        1027.33,
        1028.39,
        1030.92,
        1032.12,
        1034.52,
        1034.89,
        1035.25,
        1036.01,
        1036.22,
        1037.54,
        1038.14,
        1039.07,
        1039.37,
        1039.6,
        1041.17,
        1042.73,
        1056.95,
        1058.03,
        1058.28,
        1158.66,
        1159.82,
        1160.28,
        1160.84,
        1161.23,
        1161.6,
        1161.91,
        1162.69,
        1162.83,
        1162.94,
        1164.36,
        1164.82,
        1165.51,
        1165.85,
        1165.89,
        1166.29,
        1166.42,
        1167.62,
        1170.35,
        1173.09,
        1175.83,
        1186.08,
        1188.64,
        1189.96,
        1273.61,
        1274.86,
        1275.79,
        1276.56,
        1277.66,
        1278.27
    ],
    "latest_levels": [
        396.14
    ],
    "channel": {
        "start_date": "2024-12-23 00:00:00",
        "end_date": "2025-07-09 00:00:00",
        "start_upper": 422.76,
        "start_lower": 351.47,
        "end_upper": 472.26,
        "end_lower": 400.98
    }
}