{
    "all_levels": [
        485.31,
        485.51,
        485.63,
        485.76,
        485.88,
        485.95,
        486.05,
        486.14,
        486.21,
        486.33,
        486.45,
        486.75,
        486.86,
        486.97,
        487.0,
        487.17,
        487.25,
        487.4,
        487.62,
        489.32,
        491.91,
        494.52,
        497.13,
        499.76,
        505.06,
        507.73,
        510.42,
        513.12,
        534.46,
        535.24,
        535.66,
        536.15,
        536.73,
        536.94,
        537.05,
        537.15,
        537.19,
        537.23,
        537.33,
        537.34,
        537.49,
        537.9,
        537.96,
        538.03,
        538.12,
        538.14,
        538.29,
        538.41,
        567.1,
        567.18,
        567.31,
        567.35,
        567.45,
        567.46,
        567.86,
        568.05,
        568.08,
        568.12,
        568.13,
        568.19,
        568.23,
        568.25,
        568.41,
        568.58,
        568.62,
        568.63,
        569.04,
        593.39,
        593.52,
        593.63,
        593.67,
        593.78,
        593.84,
        594.01,
        594.12,
        594.23,
        594.27,
        594.28,
        594.29,
        594.63,
        594.7,
        594.71,
        594.76,
        594.81,
        594.83,
        595.09,
        595.18,
        595.75,
        599.69,
        599.71,
        599.72,
        599.92,
        599.99,
        600.11,
        600.14,
        600.33,
        600.35,
        600.42,
        600.44,
        603.06,
        603.94,
        604.32,
        604.82,
        604.92,
        605.07,
        605.33,
        605.43,
        605.53,
        605.54,
        605.74,
        606.42,
        606.64,
        606.74,
        607.18,
        607.39,
        610.01,
        610.18,
        610.3,
        614.89,
        614.99,
        615.3,
        619.11,
        619.61,
        619.78,
        619.93,
        619.99,
        620.01,
        620.02,
        620.09,
        620.16,
        620.23,
        620.27,
        620.32,
        620.34,
        620.58,
        621.15,
        621.55,
        622.71,
        623.87,
        624.94,
        625.0,
        625.03,
        625.08,
        625.22,
        625.31,
        625.35,
        625.87,
        625.98,
        626.84,
        627.03,
        627.97,
        628.27,
        629.25,
        629.38,
        629.47,
        629.52,
        629.53,
        629.63,
        629.78,
        629.83,
        629.91,
        629.93,
        630.02,
        630.06,
        630.07,
        630.1,
        630.23,
        630.25,
        630.27,
        630.34,
        630.35,
        630.38,
        630.39,
        630.43,
        630.54,
        630.61,
        630.93,
        631.0,
        631.76,
        633.68,
        635.07,
        637.03,
        697.15,
        697.37,
        697.53,
        697.58,
        697.59,
        697.7,
        697.73,
        697.92,
        697.93,
        698.16,
        698.4,
        698.48,
        698.69,
        698.8,
        698.81,
        698.9,
        698.92,
        699.04,
        726.85,
        730.69,
        734.56,
        738.44,
        742.35,
        746.28,
        750.23,
        779.11,
        779.19,
        779.22,
        779.36,
        779.44,
        779.62,
        779.66,
        779.82,
        780.09,
        780.12,
        780.17,
        780.23,
        780.26,
        780.31,
        780.45,
        780.51,
        780.56,
        780.76,
        780.88,
        786.74,
        798.89,
        799.19,
        799.23,
        799.29,
        799.3,
        799.31,
        799.32,
        799.35,
        799.36,
        799.38,
        799.56,
        799.63,
        799.67,
        799.99,
        800.57,
        800.81,
        800.9,
        800.91,
        801.01,
        869.89,
        869.97,
        870.01,
        870.15,
        870.23,
        870.32,
        870.62,
        870.65,
        870.96,
        871.04,
        871.12,
        871.18,
        871.23,
        871.56,
        871.73,
        872.21,
        872.27,
        934.05,
        934.08,
        934.11,
        934.12,
        934.14,
        934.25,
        934.46,
        934.61,
        934.73,
        934.77,
        934.89,
        934.91,
        937.17,
        937.39,
        938.16,
        938.18,
        939.35,
        939.46,
        939.61,
        939.85,
        940.23,
        940.63,
        947.39,
        948.16,
        948.17,
        948.28,
        948.4,
        948.42,
        948.43,
        948.48,
        948.49,
        948.59,
        948.69,
        948.73,
        948.78,
        948.8,
        949.03,
        949.76,
        949.86,
        950.0,
        951.3,
        957.5,
        957.95,
        957.96,
        958.13,
        958.14,
        958.21,
        958.24,
        958.25,
        958.31,
        958.38,
        958.47,
        967.79,
        968.28,
        968.37,
        968.47,
        968.53,
        968.57,
        968.62,
        968.64,
        968.66,
        968.85,
        973.84,
        973.97,
        974.47,
        974.59,
        975.94,
        977.27,
        979.45,
        979.48,
        979.5,
        979.95,
        981.87,
        983.22,
        988.57,
        989.26,
        989.41,
        989.82,
        989.87,
        989.96,
        990.04
    ],
    "latest_levels": [
        786.74
    ],
    "channel": {
        "start_date": "2024-12-23 00:00:00",
        "end_date": "2025-07-09 00:00:00",
        "start_upper": 634.7,
        "start_lower": 422.39,
        "end_upper": 1104.78,
        "end_lower": 892.46
    }
}