{
    "all_levels": [
        187.34,
        187.37,
        187.45,
        187.47,
        187.5,
        187.52,
        187.54,
        187.55,
        187.57,
        187.6,
        187.61,
        187.66,
        187.71,
        187.88,
        187.97,
        188.03,
        188.05,
        201.71,
        201.99,
        202.04,
        202.08,
        202.09,
        202.16,
        202.17,
        202.21,
        202.25,
        202.31,
        202.32,
        202.33,
        212.63,
        213.17,
        213.21,
        213.23,
        213.3,
        213.35,
        213.5,
        213.54,
        213.61,
        213.62,
        213.68,
        213.69,
        213.86,
        214.12,
        214.18,
        214.19,
        214.38,
        214.5,
        214.9,
        215.0,
        215.01,
        215.33,
        215.52,
        215.63,
        215.7,
        215.83,
        215.9,
        215.95,
        216.0,
        216.02,
        216.04,
        216.07,
        216.18,
        216.23,
        216.25,
        216.33,
        216.35,
        216.47,
        216.55,
        216.6,
        216.62,
        216.72,
        216.79,
        216.95,
        216.99,
        217.17,
        217.88,
        218.77,
        218.97,
        219.67,
        231.91,
        232.0,
        232.01,
        232.08,
        232.26,
        232.38,
        232.47,
        232.58,
        233.22,
        234.21,
        235.01,
        235.76,
        236.12,
        236.29,
        236.39,
        237.11,
        237.21,
        237.44,
        237.6,
        237.7,
        237.71,
        237.75,
        237.9,
        237.92,
        238.19,
        238.3,
        238.68,
        238.76,
        238.78,
        239.06,
        239.14,
        239.17,
        239.34,
        239.44,
        239.46,
        239.54,
        239.62,
        239.77,
        239.85,
        239.86,
        243.76,
        243.87,
        243.91,
        243.92,
        243.95,
        243.97,
        244.09,
        250.16,
        250.36,
        250.41,
        259.89,
        260.14,
        268.2,
        268.37,
        268.38,
        268.41,
        268.49,
        268.8,
        268.88,
        268.93,
        293.93,
        295.94,
        295.95,
        296.02,
        296.03,
        296.04,
        296.12,
        296.94,
        297.63,
        297.87,
        297.95,
        297.96,
        297.99,
        298.0,
        298.02,
        298.03,
        298.04,
        298.08,
        298.17,
        298.39,
        298.64,
        299.2,
        299.41,
        299.42,
        299.57,
        299.73,
        299.94,
        299.96,
        299.97,
        299.98,
        299.99,
        300.0,
        300.01,
        300.02,
        300.04,
        300.05,
        300.15,
        300.18,
        300.65,
        301.9,
        301.95,
        301.96,
        301.97,
        301.98,
        301.99,
        302.0,
        302.02,
        302.04,
        302.07,
        303.15,
        303.75,
        303.83,
        303.89,
        303.92,
        303.94,
        303.95,
        303.96,
        303.97,
        303.98,
        304.0,
        304.01,
        304.03,
        304.04,
        304.05,
        304.21,
        304.41,
        305.67,
        305.92,
        305.95,
        305.96,
        305.97,
        305.98,
        306.0,
        306.01,
        306.04,
        306.19,
        306.94,
        307.88,
        307.9,
        307.96,
        307.97,
        308.0,
        308.01,
        308.03,
        308.04,
        308.12,
        308.21,
        308.58,
        309.27,
        309.49,
        309.93,
        309.95,
        309.96,
        310.0,
        310.01,
        310.03,
        310.05,
        310.06,
        310.07,
        310.51,
        310.77,
        310.79,
        310.98,
        311.73,
        311.96,
        312.02,
        312.03,
        312.06,
        312.07,
        312.1,
        312.57,
        312.78,
        313.14,
        313.36,
        313.59,
        313.73,
        313.76,
        313.94,
        313.95,
        313.97,
        313.98,
        313.99,
        314.0,
        314.04,
        314.1,
        314.17,
        315.9,
        315.92,
        315.95,
        315.97,
        316.04,
        316.08,
        317.95,
        317.96,
        318.0,
        318.03,
        318.1,
        369.48,
        369.5,
        370.65,
        370.72,
        370.78,
        371.82,
        373.0,
        374.18
    ],
    "latest_levels": [
        236.39
    ],
    "channel": {
        "start_date": "2024-12-23 00:00:00",
        "end_date": "2025-07-09 00:00:00",
        "start_upper": 211.69,
        "start_lower": 164.47,
        "end_upper": 429.23,
        "end_lower": 382.01
    }
}