{
    "all_levels": [
        2413.37,
        2415.36,
        2415.56,
        2417.15,
        2417.73,
        2418.69,
        2418.85,
        2419.43,
        2419.72,
        2419.96,
        2420.66,
        2420.73,
        2421.23,
        2421.26,
        2422.15,
        2422.89,
        2423.14,
        2423.41,
        2425.0,
        2428.78,
        2429.21,
        2432.42,
        2432.56,
        2433.01,
        2433.35,
        2433.75,
        2435.31,
        2435.64,
        2435.74,
        2447.17,
        2449.73,
        2450.11,
        2450.17,
        2450.54,
        2451.39,
        2451.86,
        2452.4,
        2530.91,
        2534.26,
        2534.42,
        2534.98,
        2536.61,
        2536.63,
        2537.61,
        2629.89,
        2633.17,
        2633.18,
        2633.33,
        2633.38,
        2633.54,
        2634.26,
        2635.96,
        2637.65,
        2641.76,
        2645.87,
        2646.15,
        2646.4,
        2647.24,
        2650.63,
        2653.14,
        2653.53,
        2653.55,
        2653.88,
        2654.02,
        2655.48,
        2655.86,
        2657.03,
        2657.15,
        2671.26,
        2683.91,
        2684.42,
        2685.0,
        2685.12,
        2685.99,
        2686.01,
        2686.02,
        2686.19,
        2686.23,
        2686.36,
        2686.44,
        2686.81,
        2687.23,
        2687.38,
        2687.43,
        2687.61,
        2688.4,
        2688.65,
        2688.92,
        2689.22,
        2689.71,
        2690.21,
        2690.34,
        2690.44,
        2691.19,
        2693.94,
        2704.54,
        2709.86,
        2710.65,
        2712.52,
        2713.42,
        2716.19,
        2718.33,
        2718.68,
        2718.96,
        2719.42,
        2719.86,
        2719.98,
        2720.12,
        2721.23,
        2721.67,
        2721.93,
        2722.49,
        2756.84,
        2762.84,
        2768.85,
        2772.81,
        2774.17,
        2774.88,
        2776.37,
        2776.48,
        2777.75,
        2777.91,
        2779.28,
        2780.31,
        2780.44,
        2780.45,
        2780.92,
        2781.56,
        2781.75,
        2782.02,
        2782.97,
        2783.06,
        2786.86,
        2790.65,
        2794.46,
        2798.26,
        2799.77,
        2800.9,
        2801.67,
        2867.08,
        2867.7,
        2870.32,
        2870.85,
        2874.61,
        2923.5,
        2927.37,
        2927.38,
        2927.58,
        2927.83,
        2928.08,
        2929.82,
        2930.44,
        2931.25,
        2932.14,
        2932.28,
        2933.45,
        2933.88,
        2936.03,
        3058.0,
        3069.53,
        3078.3,
        3078.92,
        3079.67,
        3080.21,
        3080.64,
        3080.8,
        3081.28,
        3081.84,
        3081.95,
        3082.1,
        3082.27,
        3082.38,
        3082.82,
        3082.87,
        3083.26,
        3083.27,
        3084.16,
        3086.46,
        3148.31,
        3394.55,
        3396.77,
        3400.36,
        3401.12,
        3403.01,
        3403.27,
        3403.29,
        3471.44,
        3477.93,
        3478.69,
        3479.0,
        3481.43,
        3481.77,
        3482.05,
        3482.19,
        3482.82,
        3483.43,
        3483.46,
        3483.89,
        3484.0,
        3484.06,
        3484.08,
        3484.11,
        3485.35,
        3485.5,
        3485.59,
        3486.57,
        3487.04,
        3489.76,
        3494.16,
        3687.43,
        3688.72,
        3689.36,
        3689.63,
        3691.17,
        3691.34,
        3691.49,
        3691.87,
        3691.88,
        3692.36,
        3692.73,
        3697.39,
        3697.81,
        3704.15,
        3749.32,
        3751.96,
        3753.62,
        3755.14,
        3756.06,
        3757.43,
        3758.14,
        3759.01,
        3759.64,
        3761.44,
        3762.9,
        3763.12,
        3764.1,
        3764.41,
        3765.43,
        3768.81,
        3769.46,
        3770.24,
        3801.82,
        3805.61,
        3826.57,
        3839.69,
        3844.97,
        3846.27,
        3852.86,
        3853.34,
        3861.73,
        4223.1,
        4223.61,
        4224.35,
        4227.34,
        4229.66,
        4229.77,
        4234.3,
        4235.01,
        4235.71,
        4236.45,
        4237.32,
        4238.5,
        4240.18,
        4240.86
    ],
    "latest_levels": [
        2447.17,
        2687.61
    ],
    "channel": {
        "start_date": "2024-12-23 00:00:00",
        "end_date": "2025-07-09 00:00:00",
        "start_upper": 2757.41,
        "start_lower": 2481.73,
        "end_upper": 2848.93,
        "end_lower": 2573.25
    }
}