{
    "all_levels": [
        841.31,
        841.53,
        841.76,
        841.87,
        842.01,
        842.31,
        842.55,
        842.78,
        843.17,
        843.45,
        844.33,
        844.47,
        844.62,
        844.8,
        846.45,
        847.52,
        847.61,
        847.74,
        851.16,
        851.33,
        855.08,
        925.78,
        927.29,
        927.36,
        927.51,
        927.68,
        927.88,
        928.28,
        928.42,
        929.82,
        981.02,
        983.95,
        984.16,
        985.4,
        985.49,
        985.78,
        986.82,
        986.88,
        987.1,
        987.16,
        987.48,
        987.7,
        989.24,
        989.4,
        989.72,
        989.83,
        990.27,
        990.45,
        990.72,
        991.07,
        991.1,
        991.2,
        991.32,
        991.96,
        992.02,
        992.14,
        992.75,
        992.78,
        992.81,
        992.93,
        993.08,
        993.22,
        993.27,
        993.3,
        993.51,
        993.78,
        993.82,
        994.17,
        994.2,
        994.39,
        994.52,
        994.86,
        994.94,
        995.36,
        995.67,
        995.74,
        995.95,
        996.24,
        996.27,
        996.28,
        996.38,
        996.7,
        996.99,
        997.44,
        997.51,
        997.72,
        998.42,
        998.57,
        998.68,
        998.71,
        999.67,
        1000.57,
        1001.69,
        1002.06,
        1004.68,
        1005.29,
        1005.58,
        1006.91,
        1006.97,
        1008.35,
        1033.4,
        1035.63,
        1037.86,
        1040.1,
        1042.34,
        1043.33,
        1044.12,
        1045.67,
        1046.0,
        1046.09,
        1046.33,
        1046.97,
        1047.31,
        1047.42,
        1047.84,
        1048.17,
        1048.84,
        1049.09,
        1049.68,
        1050.26,
        1057.4,
        1058.83,
        1060.26,
        1061.7,
        1061.86,
        1063.9,
        1064.15,
        1065.57,
        1067.99,
        1069.6,
        1070.35,
        1070.68,
        1071.26,
        1072.26,
        1072.44,
        1072.91,
        1073.21,
        1073.64,
        1073.66,
        1073.69,
        1073.72,
        1073.77,
        1073.83,
        1073.88,
        1073.91,
        1073.96,
        1074.02,
        1074.09,
        1074.19,
        1074.33,
        1074.39,
        1074.59,
        1074.61,
        1074.63,
        1074.76,
        1074.86,
        1074.91,
        1074.97,
        1075.07,
        1075.12,
        1075.81,
        1075.89,
        1076.07,
        1078.02,
        1080.16,
        1082.29,
        1084.44,
        1086.58,
        1121.75,
        1121.92,
        1123.56,
        1123.85,
        1125.37,
        1125.38,
        1125.44,
        1125.49,
        1125.56,
        1125.74,
        1125.76,
        1125.79,
        1125.84,
        1125.95,
        1125.99,
        1126.06,
        1126.14,
        1126.87,
        1127.79,
        1128.18,
        1129.88,
        1130.41,
        1130.8,
        1132.82,
        1183.01,
        1183.41,
        1183.47,
        1183.49,
        1183.83,
        1184.08,
        1184.37,
        1184.91,
        1185.37,
        1185.54,
        1185.98,
        1186.08,
        1186.09,
        1186.36,
        1187.0,
        1187.97,
        1188.05,
        1188.2,
        1188.77,
        1189.52,
        1190.03,
        1192.39,
        1298.65,
        1304.5,
        1305.16,
        1305.48,
        1307.08,
        1308.03,
        1308.2,
        1308.5,
        1308.61,
        1308.89,
        1308.99,
        1309.59,
        1310.92,
        1311.09,
        1312.26,
        1313.69,
        1314.27,
        1316.28,
        1316.91,
        1318.89,
        1321.5,
        1337.8,
        1341.15,
        1341.73,
        1341.85,
        1342.14,
        1342.18,
        1342.68,
        1343.25,
        1343.58,
        1343.76,
        1345.15,
        1345.5,
        1346.29,
        1349.16,
        1355.24,
        1355.32,
        1706.5,
        1707.98,
        1709.93,
        1719.51,
        1722.18,
        1722.56,
        1722.8,
        1723.76,
        1726.93,
        1727.15,
        1729.2,
        1729.92
    ],
    "latest_levels": [
        985.78,
        1706.5
    ],
    "channel": {
        "start_date": "2024-12-23 00:00:00",
        "end_date": "2025-07-09 00:00:00",
        "start_upper": 719.72,
        "start_lower": 203.76,
        "end_upper": 3123.74,
        "end_lower": 2607.78
    }
}