{
    "all_levels": [
        254.88,
        254.99,
        255.17,
        257.04,
        258.19,
        258.82,
        259.79,
        261.38,
        262.57,
        262.64,
        263.95,
        264.31,
        733.76,
        734.5,
        735.09,
        762.13,
        768.16,
        774.23,
        775.99,
        776.19,
        779.38,
        780.15,
        780.35,
        783.0,
        784.1,
        788.83,
        794.7,
        800.62,
        806.57,
        807.36,
        809.62,
        809.64,
        809.82,
        810.89,
        811.1,
        812.58,
        812.73,
        814.11,
        814.4,
        815.04,
        815.91,
        816.78,
        816.85,
        817.23,
        822.27,
        823.14,
        824.78,
        825.31,
        825.4,
        826.12,
        826.24,
        826.63,
        826.75,
        827.14,
        827.3,
        829.83,
        830.55,
        830.91,
        832.35,
        832.37,
        834.37,
        834.43,
        834.68,
        834.91,
        836.81,
        838.15,
        838.35,
        838.4,
        841.88,
        842.44,
        842.96,
        843.27,
        848.39,
        853.54,
        856.02,
        856.16,
        861.35,
        866.71,
        973.37,
        975.46,
        977.24,
        978.44,
        979.66,
        981.13,
        982.21,
        982.86,
        1102.89,
        1105.24,
        1105.25,
        1105.46,
        1105.64,
        1105.71,
        1106.08,
        1106.09,
        1106.87,
        1107.19,
        1107.58,
        1108.03,
        1108.56,
        1108.7,
        1109.04,
        1109.12,
        1109.37,
        1109.53,
        1109.64,
        1109.91,
        1109.99,
        1110.11,
        1110.33,
        1110.78,
        1111.29,
        1112.29,
        1114.05,
        1117.67,
        1271.69,
        1286.24,
        1293.21,
        1308.51,
        1323.99,
        1339.65,
        1355.5,
        1368.07,
        1371.54,
        1372.79,
        1381.81,
        1387.72,
        1389.76,
        1396.47,
        1399.75,
        1403.2,
        1409.97,
        1412.31,
        1414.11,
        1414.53,
        1414.64,
        1414.79,
        1415.08,
        1415.69,
        1416.27,
        1416.78,
        1417.01,
        1417.1,
        1417.93,
        1418.4,
        1418.75,
        1418.92,
        1419.28,
        1419.33,
        1421.14,
        1424.71,
        1430.11,
        1435.53,
        1436.34,
        1440.97,
        1446.43,
        1451.91,
        1462.94,
        1468.49,
        1473.88,
        1474.05,
        1479.64,
        1485.25,
        1490.88,
        1493.02,
        1512.4,
        1532.04,
        1551.93,
        1572.08,
        1592.49,
        1613.17,
        1634.11,
        1655.33,
        1676.82,
        1698.59,
        1720.65,
        1737.21,
        1737.53,
        1738.36,
        1739.02,
        1740.45,
        1742.38,
        1742.99,
        1743.41,
        1765.62,
        1788.54,
        1811.77,
        1835.29,
        1839.04,
        1843.96,
        1851.87,
        1853.56,
        1855.27,
        1858.25,
        1858.36,
        1860.56,
        1861.77,
        1867.35,
        1874.19,
        1875.88,
        1877.65,
        1879.51,
        1891.75,
        1904.06,
        1908.77,
        1919.93,
        1931.16,
        1933.15,
        1935.43,
        1935.59,
        1937.06,
        1937.19,
        1941.05,
        1942.93,
        1943.59,
        1943.68,
        1950.29,
        2425.79,
        2426.23,
        2431.31,
        2435.12,
        2437.6,
        2439.11,
        2440.06,
        2441.87,
        2442.75,
        2444.6,
        2444.98,
        2445.6,
        2446.37,
        2448.48,
        2449.18,
        2449.86,
        2450.27,
        2451.41,
        2452.97,
        2455.37,
        2459.41,
        2459.74,
        2461.82,
        2464.31,
        2464.82,
        2466.19,
        2466.46,
        2471.04,
        2471.42,
        2472.45,
        2473.37,
        2475.03,
        2475.3,
        2483.8,
        2483.95,
        2487.44,
        2501.6,
        2509.98,
        2515.84,
        2523.09,
        2530.16,
        2536.27,
        2544.55,
        2559.04,
        2573.6,
        2588.25,
        3845.44,
        3864.46,
        3876.21,
        3894.92,
        4873.44,
        4890.43,
        4897.55,
        4915.98,
        4921.79,
        4941.67,
        4947.35,
        4949.64,
        4949.72,
        4956.54,
        4960.32,
        4963.64,
        4964.9,
        4965.32,
        4967.49,
        4975.03,
        4975.77,
        4980.98,
        4982.7,
        4982.9,
        4983.52,
        4991.51,
        4993.44,
        4998.7,
        4999.15
    ],
    "latest_levels": [
        2464.82,
        3876.21
    ],
    "channel": {
        "start_date": "2024-11-21 00:00:00",
        "end_date": "2025-06-05 00:00:00",
        "start_upper": 4710.07,
        "start_lower": 4098.42,
        "end_upper": 2755.41,
        "end_lower": 2143.76
    }
}