{
    "all_levels": [
        367.24,
        367.95,
        381.74,
        382.53,
        383.05,
        383.12,
        383.15,
        383.18,
        383.27,
        383.71,
        383.85,
        384.02,
        384.38,
        384.76,
        385.51,
        423.34,
        423.93,
        424.18,
        424.46,
        424.53,
        424.95,
        424.98,
        425.79,
        426.61,
        426.81,
        427.23,
        428.08,
        428.15,
        429.23,
        429.54,
        430.34,
        430.54,
        430.66,
        430.89,
        431.13,
        431.17,
        431.28,
        432.19,
        435.96,
        454.64,
        455.28,
        456.55,
        456.59,
        457.34,
        457.37,
        457.72,
        457.83,
        457.85,
        457.87,
        458.09,
        458.21,
        458.26,
        459.0,
        459.15,
        459.19,
        459.31,
        459.64,
        460.04,
        460.94,
        461.83,
        462.73,
        463.63,
        464.53,
        480.8,
        480.91,
        481.07,
        481.23,
        481.47,
        481.75,
        482.02,
        482.13,
        482.15,
        482.4,
        482.49,
        482.81,
        482.88,
        483.01,
        483.2,
        483.23,
        483.29,
        483.33,
        483.44,
        483.49,
        483.6,
        483.68,
        483.78,
        484.01,
        484.14,
        529.59,
        529.68,
        529.81,
        529.85,
        529.88,
        529.99,
        530.0,
        530.03,
        530.07,
        530.25,
        530.29,
        530.47,
        530.48,
        530.51,
        530.58,
        530.61,
        530.62,
        530.77,
        530.84,
        530.86,
        530.93,
        531.0,
        531.12,
        531.16,
        531.22,
        531.24,
        532.19,
        574.15,
        610.97,
        611.78,
        612.09,
        612.23,
        612.26,
        613.05,
        613.49,
        614.02,
        614.76,
        614.79,
        614.98,
        615.37,
        615.67,
        615.74,
        616.19,
        617.01,
        617.29,
        617.83,
        617.89,
        618.66,
        619.48,
        619.84,
        620.31,
        620.82,
        621.14,
        621.79,
        645.93,
        646.12,
        646.21,
        646.47,
        646.64,
        646.78,
        665.74,
        665.84,
        665.96,
        666.13,
        666.47,
        666.99,
        667.05,
        667.1,
        667.5,
        667.56,
        667.68,
        667.73,
        667.95,
        668.01,
        668.12,
        668.14,
        668.16,
        668.21,
        668.5,
        668.68,
        669.23,
        669.29,
        669.42,
        669.79,
        670.16,
        670.36,
        670.61,
        671.32,
        671.4,
        671.42,
        671.47,
        671.91,
        672.05,
        672.44,
        674.03,
        676.15,
        678.29,
        680.13,
        680.41,
        680.59,
        680.96,
        681.0,
        681.01,
        681.17,
        681.2,
        681.31,
        681.34,
        681.47,
        681.77,
        682.37,
        682.97,
        683.57,
        684.17,
        684.77,
        685.37,
        699.87,
        699.88,
        699.95,
        700.04,
        700.47,
        700.7,
        701.61,
        701.94,
        702.07,
        702.17,
        702.61,
        703.41,
        703.62,
        703.93,
        704.08,
        704.2,
        704.36,
        704.76,
        704.88,
        704.9,
        705.04,
        705.17,
        705.23,
        705.41,
        705.52,
        705.57,
        705.72,
        705.74,
        706.0,
        706.11,
        706.17,
        706.29
    ],
    "latest_levels": [
        574.15,
        616.19
    ],
    "channel": {
        "start_date": "2024-12-23 00:00:00",
        "end_date": "2025-07-09 00:00:00",
        "start_upper": 654.45,
        "start_lower": 570.41,
        "end_upper": 638.84,
        "end_lower": 554.8
    }
}